{
  "python": {
    "name": "Python",
    "config": {
      "code": "print('Hello World')"
    },
    "output": "Hello World",
    "stdout": "Hello World"
  },
  "javascript": {
    "name": "JavaScript",
    "config": {
      "code": "console.log('Hello World')"
    },
    "stdout": "Hello World",
    "output": "Hello World"
  },
  "graphql": {
    "name": "GraphQL",
    "config": {
      "code": "query {\n  user(id: \"1\") {\n    id\n    name\n    email\n  }\n}"
    },
    "stdout": "Hello World",
    "output": "Hello World"
  },
  "postgres": {
    "name": "Postgres",
    "config": {
      "code": "SELECT * FROM test_table WHERE id = 1 AND name = 'John'"
    },
    "stdout": "Hello World",
    "output": "Hello World"
  },
  "rest": {
    "name": "REST API",
    "config": {
      "code": "console.log('Hello World')"
    },
    "stdout": "Hello World",
    "output": "Hello World"
  }
}
